[
  {
    "ContainingType": "WorkNestHRMS.Controllers.AdminController",
    "Method": "GetAdminData",
    "RelativePath": "api/admin/data",
    "HttpMethod": "GET",
    "IsController": true,
    "Order": 0,
    "Parameters": [],
    "ReturnTypes": []
  },
  {
    "ContainingType": "WorkNestHRMS.Controllers.AuthController",
    "Method": "Login",
    "RelativePath": "api/auth/login",
    "HttpMethod": "POST",
    "IsController": true,
    "Order": 0,
    "Parameters": [
      {
        "Name": "loginDto",
        "Type": "WorkNestHRMS.Models.LoginDto",
        "IsRequired": true
      }
    ],
    "ReturnTypes": []
  },
  {
    "ContainingType": "WorkNestHRMS.Controllers.AuthController",
    "Method": "RefreshToken",
    "RelativePath": "api/auth/refresh",
    "HttpMethod": "POST",
    "IsController": true,
    "Order": 0,
    "Parameters": [
      {
        "Name": "expiredToken",
        "Type": "System.String",
        "IsRequired": true
      }
    ],
    "ReturnTypes": []
  },
  {
    "ContainingType": "WorkNestHRMS.Controllers.AuthController",
    "Method": "Register",
    "RelativePath": "api/auth/register",
    "HttpMethod": "POST",
    "IsController": true,
    "Order": 0,
    "Parameters": [
      {
        "Name": "registerDto",
        "Type": "WorkNestHRMS.Models.RegisterDto",
        "IsRequired": true
      }
    ],
    "ReturnTypes": []
  },
  {
    "ContainingType": "WorkNestHRMS.Controllers.EmployeesController",
    "Method": "GetEmployees",
    "RelativePath": "api/employee",
    "HttpMethod": "GET",
    "IsController": true,
    "Order": 0,
    "Parameters": [],
    "ReturnTypes": [
      {
        "Type": "System.Collections.Generic.IEnumerable\u00601[[WorkNestHRMS.Models.Employee, WorkNestHRMS, Version=1.0.0.0, Culture=neutral, PublicKeyToken=null]]",
        "MediaTypes": [
          "text/plain",
          "application/json",
          "text/json"
        ],
        "StatusCode": 200
      }
    ]
  },
  {
    "ContainingType": "WorkNestHRMS.Controllers.EmployeesController",
    "Method": "CreateEmployee",
    "RelativePath": "api/employee",
    "HttpMethod": "POST",
    "IsController": true,
    "Order": 0,
    "Parameters": [
      {
        "Name": "employee",
        "Type": "WorkNestHRMS.Models.Employee",
        "IsRequired": true
      }
    ],
    "ReturnTypes": []
  },
  {
    "ContainingType": "WorkNestHRMS.Controllers.EmployeesController",
    "Method": "GetEmployee",
    "RelativePath": "api/employee/{id}",
    "HttpMethod": "GET",
    "IsController": true,
    "Order": 0,
    "Parameters": [
      {
        "Name": "id",
        "Type": "System.Int32",
        "IsRequired": true
      }
    ],
    "ReturnTypes": [
      {
        "Type": "WorkNestHRMS.Models.Employee",
        "MediaTypes": [
          "text/plain",
          "application/json",
          "text/json"
        ],
        "StatusCode": 200
      }
    ]
  },
  {
    "ContainingType": "WorkNestHRMS.Controllers.EmployeesController",
    "Method": "UpdateEmployee",
    "RelativePath": "api/employee/{id}",
    "HttpMethod": "PUT",
    "IsController": true,
    "Order": 0,
    "Parameters": [
      {
        "Name": "id",
        "Type": "System.Int32",
        "IsRequired": true
      },
      {
        "Name": "employee",
        "Type": "WorkNestHRMS.Models.Employee",
        "IsRequired": true
      }
    ],
    "ReturnTypes": []
  },
  {
    "ContainingType": "WorkNestHRMS.Controllers.HomeController",
    "Method": "GetHomeData",
    "RelativePath": "api/home",
    "HttpMethod": "GET",
    "IsController": true,
    "Order": 0,
    "Parameters": [],
    "ReturnTypes": []
  },
  {
    "ContainingType": "WorkNestHRMS.Controllers.HomeController",
    "Method": "GetUserTasks",
    "RelativePath": "api/home/tasks",
    "HttpMethod": "GET",
    "IsController": true,
    "Order": 0,
    "Parameters": [],
    "ReturnTypes": []
  },
  {
    "ContainingType": "WorkNestHRMS.Controllers.UserTasksController",
    "Method": "GetTasksForLoggedUser",
    "RelativePath": "api/user-tasks",
    "HttpMethod": "GET",
    "IsController": true,
    "Order": 0,
    "Parameters": [],
    "ReturnTypes": []
  },
  {
    "ContainingType": "WorkNestHRMS.Controllers.UserController",
    "Method": "GetUserData",
    "RelativePath": "api/user/data",
    "HttpMethod": "GET",
    "IsController": true,
    "Order": 0,
    "Parameters": [],
    "ReturnTypes": []
  },
  {
    "ContainingType": "WorkNestHRMS.Controllers.WorkplaceController",
    "Method": "GetWorkplaceDetails",
    "RelativePath": "api/workplaces/{id}",
    "HttpMethod": "GET",
    "IsController": true,
    "Order": 0,
    "Parameters": [
      {
        "Name": "id",
        "Type": "System.Int32",
        "IsRequired": true
      }
    ],
    "ReturnTypes": []
  },
  {
    "ContainingType": "WorkNestHRMS.Controllers.WorkplaceController",
    "Method": "UpdateWorkplace",
    "RelativePath": "api/workplaces/{id}",
    "HttpMethod": "PUT",
    "IsController": true,
    "Order": 0,
    "Parameters": [
      {
        "Name": "id",
        "Type": "System.Int32",
        "IsRequired": true
      },
      {
        "Name": "workplaceDto",
        "Type": "WorkNestHRMS.Models.WorkplaceDto",
        "IsRequired": true
      }
    ],
    "ReturnTypes": []
  },
  {
    "ContainingType": "WorkNestHRMS.Controllers.WorkplaceController",
    "Method": "DeleteWorkplace",
    "RelativePath": "api/workplaces/{id}",
    "HttpMethod": "DELETE",
    "IsController": true,
    "Order": 0,
    "Parameters": [
      {
        "Name": "id",
        "Type": "System.Int32",
        "IsRequired": true
      }
    ],
    "ReturnTypes": []
  },
  {
    "ContainingType": "WorkNestHRMS.Controllers.WorkplaceController",
    "Method": "AddUserToWorkplace",
    "RelativePath": "api/workplaces/{id}/add-user",
    "HttpMethod": "POST",
    "IsController": true,
    "Order": 0,
    "Parameters": [
      {
        "Name": "id",
        "Type": "System.Int32",
        "IsRequired": true
      },
      {
        "Name": "userIdToAdd",
        "Type": "System.Int32",
        "IsRequired": true
      }
    ],
    "ReturnTypes": []
  },
  {
    "ContainingType": "WorkNestHRMS.Controllers.WorkplaceController",
    "Method": "SearchUsers",
    "RelativePath": "api/workplaces/{id}/search-users",
    "HttpMethod": "GET",
    "IsController": true,
    "Order": 0,
    "Parameters": [
      {
        "Name": "id",
        "Type": "System.Int32",
        "IsRequired": true
      },
      {
        "Name": "query",
        "Type": "System.String",
        "IsRequired": false
      }
    ],
    "ReturnTypes": []
  },
  {
    "ContainingType": "WorkNestHRMS.Controllers.WorkplaceController",
    "Method": "SearchUsersWorkGroup",
    "RelativePath": "api/workplaces/{id}/search-users-workgroup",
    "HttpMethod": "GET",
    "IsController": true,
    "Order": 0,
    "Parameters": [
      {
        "Name": "id",
        "Type": "System.Int32",
        "IsRequired": true
      },
      {
        "Name": "query",
        "Type": "System.String",
        "IsRequired": false
      }
    ],
    "ReturnTypes": []
  },
  {
    "ContainingType": "WorkNestHRMS.Controllers.WorkplaceController",
    "Method": "SearchWorkGroups",
    "RelativePath": "api/workplaces/{id}/search-workgroups",
    "HttpMethod": "GET",
    "IsController": true,
    "Order": 0,
    "Parameters": [
      {
        "Name": "id",
        "Type": "System.Int32",
        "IsRequired": true
      },
      {
        "Name": "query",
        "Type": "System.String",
        "IsRequired": false
      }
    ],
    "ReturnTypes": []
  },
  {
    "ContainingType": "WorkNestHRMS.Controllers.WorkplaceController",
    "Method": "RemoveUserFromWorkplace",
    "RelativePath": "api/workplaces/{workplaceId}/remove-user/{userId}",
    "HttpMethod": "DELETE",
    "IsController": true,
    "Order": 0,
    "Parameters": [
      {
        "Name": "workplaceId",
        "Type": "System.Int32",
        "IsRequired": true
      },
      {
        "Name": "userId",
        "Type": "System.Int32",
        "IsRequired": true
      }
    ],
    "ReturnTypes": []
  },
  {
    "ContainingType": "TasksController",
    "Method": "CreateTask",
    "RelativePath": "api/workplaces/{workplaceId}/tasks",
    "HttpMethod": "POST",
    "IsController": true,
    "Order": 0,
    "Parameters": [
      {
        "Name": "workplaceId",
        "Type": "System.Int32",
        "IsRequired": true
      },
      {
        "Name": "request",
        "Type": "WorkNestHRMS.Models.TaskRequests\u002BCreateTaskRequest",
        "IsRequired": true
      }
    ],
    "ReturnTypes": []
  },
  {
    "ContainingType": "TasksController",
    "Method": "GetTasks",
    "RelativePath": "api/workplaces/{workplaceId}/tasks",
    "HttpMethod": "GET",
    "IsController": true,
    "Order": 0,
    "Parameters": [
      {
        "Name": "workplaceId",
        "Type": "System.Int32",
        "IsRequired": true
      }
    ],
    "ReturnTypes": []
  },
  {
    "ContainingType": "TasksController",
    "Method": "DeleteTask",
    "RelativePath": "api/workplaces/{workplaceId}/tasks/{taskId}",
    "HttpMethod": "DELETE",
    "IsController": true,
    "Order": 0,
    "Parameters": [
      {
        "Name": "workplaceId",
        "Type": "System.Int32",
        "IsRequired": true
      },
      {
        "Name": "taskId",
        "Type": "System.Int32",
        "IsRequired": true
      }
    ],
    "ReturnTypes": []
  },
  {
    "ContainingType": "TasksController",
    "Method": "DownloadAttachment",
    "RelativePath": "api/workplaces/{workplaceId}/tasks/{taskId}/attachments/{fileName}",
    "HttpMethod": "GET",
    "IsController": true,
    "Order": 0,
    "Parameters": [
      {
        "Name": "workplaceId",
        "Type": "System.Int32",
        "IsRequired": true
      },
      {
        "Name": "taskId",
        "Type": "System.Int32",
        "IsRequired": true
      },
      {
        "Name": "fileName",
        "Type": "System.String",
        "IsRequired": true
      }
    ],
    "ReturnTypes": []
  },
  {
    "ContainingType": "TasksController",
    "Method": "DeleteAttachment",
    "RelativePath": "api/workplaces/{workplaceId}/tasks/{taskId}/attachments/{fileName}",
    "HttpMethod": "DELETE",
    "IsController": true,
    "Order": 0,
    "Parameters": [
      {
        "Name": "workplaceId",
        "Type": "System.Int32",
        "IsRequired": true
      },
      {
        "Name": "taskId",
        "Type": "System.Int32",
        "IsRequired": true
      },
      {
        "Name": "fileName",
        "Type": "System.String",
        "IsRequired": true
      }
    ],
    "ReturnTypes": []
  },
  {
    "ContainingType": "TasksController",
    "Method": "GetTaskFile",
    "RelativePath": "api/workplaces/{workplaceId}/tasks/{taskId}/files/{fileName}",
    "HttpMethod": "GET",
    "IsController": true,
    "Order": 0,
    "Parameters": [
      {
        "Name": "workplaceId",
        "Type": "System.Int32",
        "IsRequired": true
      },
      {
        "Name": "taskId",
        "Type": "System.Int32",
        "IsRequired": true
      },
      {
        "Name": "fileName",
        "Type": "System.String",
        "IsRequired": true
      }
    ],
    "ReturnTypes": []
  },
  {
    "ContainingType": "TasksController",
    "Method": "RefreshAttachments",
    "RelativePath": "api/workplaces/{workplaceId}/tasks/{taskId}/refresh-attachments",
    "HttpMethod": "PUT",
    "IsController": true,
    "Order": 0,
    "Parameters": [
      {
        "Name": "workplaceId",
        "Type": "System.Int32",
        "IsRequired": true
      },
      {
        "Name": "taskId",
        "Type": "System.Int32",
        "IsRequired": true
      }
    ],
    "ReturnTypes": []
  },
  {
    "ContainingType": "TasksController",
    "Method": "UpdateTaskStatus",
    "RelativePath": "api/workplaces/{workplaceId}/tasks/{taskId}/status",
    "HttpMethod": "PUT",
    "IsController": true,
    "Order": 0,
    "Parameters": [
      {
        "Name": "workplaceId",
        "Type": "System.Int32",
        "IsRequired": true
      },
      {
        "Name": "taskId",
        "Type": "System.Int32",
        "IsRequired": true
      },
      {
        "Name": "request",
        "Type": "WorkNestHRMS.Models.TaskRequests\u002BUpdateTaskStatusRequest",
        "IsRequired": true
      }
    ],
    "ReturnTypes": []
  },
  {
    "ContainingType": "TasksController",
    "Method": "UploadTaskFiles",
    "RelativePath": "api/workplaces/{workplaceId}/tasks/{taskId}/upload",
    "HttpMethod": "POST",
    "IsController": true,
    "Order": 0,
    "Parameters": [
      {
        "Name": "workplaceId",
        "Type": "System.Int32",
        "IsRequired": true
      },
      {
        "Name": "taskId",
        "Type": "System.Int32",
        "IsRequired": true
      },
      {
        "Name": "files",
        "Type": "System.Collections.Generic.List\u00601[[Microsoft.AspNetCore.Http.IFormFile, Microsoft.AspNetCore.Http.Features, Version=8.0.0.0, Culture=neutral, PublicKeyToken=adb9793829ddae60]]",
        "IsRequired": false
      }
    ],
    "ReturnTypes": []
  },
  {
    "ContainingType": "WorkNestHRMS.Controllers.WorkplaceController",
    "Method": "UpdateRole",
    "RelativePath": "api/workplaces/{workplaceId}/update-role",
    "HttpMethod": "PUT",
    "IsController": true,
    "Order": 0,
    "Parameters": [
      {
        "Name": "workplaceId",
        "Type": "System.Int32",
        "IsRequired": true
      },
      {
        "Name": "request",
        "Type": "WorkNestHRMS.Controllers.WorkplaceController\u002BUpdateRoleRequest",
        "IsRequired": true
      }
    ],
    "ReturnTypes": []
  },
  {
    "ContainingType": "WorkNestHRMS.Controllers.WorkplaceController",
    "Method": "GetUserRole",
    "RelativePath": "api/workplaces/{workplaceId}/user-role",
    "HttpMethod": "GET",
    "IsController": true,
    "Order": 0,
    "Parameters": [
      {
        "Name": "workplaceId",
        "Type": "System.Int32",
        "IsRequired": true
      }
    ],
    "ReturnTypes": []
  },
  {
    "ContainingType": "WorkNestHRMS.Controllers.WorkGroupsController",
    "Method": "CreateWorkGroup",
    "RelativePath": "api/workplaces/{workplaceId}/workgroups",
    "HttpMethod": "POST",
    "IsController": true,
    "Order": 0,
    "Parameters": [
      {
        "Name": "workplaceId",
        "Type": "System.Int32",
        "IsRequired": true
      },
      {
        "Name": "request",
        "Type": "WorkNestHRMS.Models.WorkGroupRequests\u002BCreateWorkGroupRequest",
        "IsRequired": true
      }
    ],
    "ReturnTypes": []
  },
  {
    "ContainingType": "WorkNestHRMS.Controllers.WorkGroupsController",
    "Method": "GetWorkGroups",
    "RelativePath": "api/workplaces/{workplaceId}/workgroups",
    "HttpMethod": "GET",
    "IsController": true,
    "Order": 0,
    "Parameters": [
      {
        "Name": "workplaceId",
        "Type": "System.Int32",
        "IsRequired": true
      }
    ],
    "ReturnTypes": []
  },
  {
    "ContainingType": "WorkNestHRMS.Controllers.WorkGroupsController",
    "Method": "DeleteWorkGroup",
    "RelativePath": "api/workplaces/{workplaceId}/workgroups/{workGroupId}",
    "HttpMethod": "DELETE",
    "IsController": true,
    "Order": 0,
    "Parameters": [
      {
        "Name": "workplaceId",
        "Type": "System.Int32",
        "IsRequired": true
      },
      {
        "Name": "workGroupId",
        "Type": "System.Int32",
        "IsRequired": true
      }
    ],
    "ReturnTypes": []
  },
  {
    "ContainingType": "WorkNestHRMS.Controllers.WorkGroupsController",
    "Method": "AddUserToWorkGroup",
    "RelativePath": "api/workplaces/{workplaceId}/workgroups/{workGroupId}/add-user",
    "HttpMethod": "POST",
    "IsController": true,
    "Order": 0,
    "Parameters": [
      {
        "Name": "workplaceId",
        "Type": "System.Int32",
        "IsRequired": true
      },
      {
        "Name": "workGroupId",
        "Type": "System.Int32",
        "IsRequired": true
      },
      {
        "Name": "request",
        "Type": "WorkNestHRMS.Models.WorkGroupRequests\u002BAddUserToWorkGroupRequest",
        "IsRequired": true
      }
    ],
    "ReturnTypes": []
  },
  {
    "ContainingType": "WorkNestHRMS.Controllers.WorkGroupsController",
    "Method": "RemoveUserFromWorkGroup",
    "RelativePath": "api/workplaces/{workplaceId}/workgroups/{workGroupId}/remove-user",
    "HttpMethod": "POST",
    "IsController": true,
    "Order": 0,
    "Parameters": [
      {
        "Name": "workplaceId",
        "Type": "System.Int32",
        "IsRequired": true
      },
      {
        "Name": "workGroupId",
        "Type": "System.Int32",
        "IsRequired": true
      },
      {
        "Name": "request",
        "Type": "WorkNestHRMS.Models.WorkGroupRequests\u002BRemoveUserFromWorkGroupRequest",
        "IsRequired": true
      }
    ],
    "ReturnTypes": []
  },
  {
    "ContainingType": "WorkNestHRMS.Controllers.WorkGroupsController",
    "Method": "SearchUser",
    "RelativePath": "api/workplaces/{workplaceId}/workgroups/{workGroupId}/search-user",
    "HttpMethod": "GET",
    "IsController": true,
    "Order": 0,
    "Parameters": [
      {
        "Name": "workplaceId",
        "Type": "System.Int32",
        "IsRequired": true
      },
      {
        "Name": "workGroupId",
        "Type": "System.Int32",
        "IsRequired": true
      },
      {
        "Name": "lastName",
        "Type": "System.String",
        "IsRequired": false
      }
    ],
    "ReturnTypes": []
  },
  {
    "ContainingType": "WorkNestHRMS.Controllers.WorkplaceController",
    "Method": "CreateWorkplace",
    "RelativePath": "api/workplaces/create",
    "HttpMethod": "POST",
    "IsController": true,
    "Order": 0,
    "Parameters": [
      {
        "Name": "workplaceDto",
        "Type": "WorkNestHRMS.Models.WorkplaceDto",
        "IsRequired": true
      }
    ],
    "ReturnTypes": []
  },
  {
    "ContainingType": "WorkNestHRMS.Controllers.WorkplaceController",
    "Method": "GetUserWorkplaces",
    "RelativePath": "api/workplaces/my",
    "HttpMethod": "GET",
    "IsController": true,
    "Order": 0,
    "Parameters": [],
    "ReturnTypes": []
  }
]